ouva/__init__.py
ouva/command/__init__.py
ouva/command/attribute/__init__.py
ouva/command/attribute/attribute_grpc.py
ouva/command/attribute/attribute_pb2.py
ouva/command/attribute/attribute_pb2_grpc.py
ouva/command/change_room_state/__init__.py
ouva/command/change_room_state/change_room_state_grpc.py
ouva/command/change_room_state/change_room_state_pb2.py
ouva/command/change_room_state/change_room_state_pb2_grpc.py
ouva/common/__init__.py
ouva/common/coordinate_grpc.py
ouva/common/coordinate_pb2.py
ouva/common/coordinate_pb2_grpc.py
ouva/event/__init__.py
ouva/event/frame/__init__.py
ouva/event/frame/frame_meta_grpc.py
ouva/event/frame/frame_meta_pb2.py
ouva/event/frame/frame_meta_pb2_grpc.py
ouva/event/notification/__init__.py
ouva/event/notification/notification_cancellation_grpc.py
ouva/event/notification/notification_cancellation_pb2.py
ouva/event/notification/notification_cancellation_pb2_grpc.py
ouva/event/notification/notification_grpc.py
ouva/event/notification/notification_pb2.py
ouva/event/notification/notification_pb2_grpc.py
ouva/event/patient_risk/__init__.py
ouva/event/patient_risk/patient_risk_grpc.py
ouva/event/patient_risk/patient_risk_pb2.py
ouva/event/patient_risk/patient_risk_pb2_grpc.py
ouva/event/patient_session/__init__.py
ouva/event/patient_session/patient_session_grpc.py
ouva/event/patient_session/patient_session_pb2.py
ouva/event/patient_session/patient_session_pb2_grpc.py
ouva/event/patient_status/__init__.py
ouva/event/patient_status/patient_status_grpc.py
ouva/event/patient_status/patient_status_pb2.py
ouva/event/patient_status/patient_status_pb2_grpc.py
ouva/event/person_count/__init__.py
ouva/event/person_count/person_count_grpc.py
ouva/event/person_count/person_count_pb2.py
ouva/event/person_count/person_count_pb2_grpc.py
ouva/event/person_metadata/__init__.py
ouva/event/person_metadata/person_metadata_grpc.py
ouva/event/person_metadata/person_metadata_pb2.py
ouva/event/person_metadata/person_metadata_pb2_grpc.py
ouva_rpc-1.23.3.dist-info/METADATA
ouva_rpc-1.23.3.dist-info/WHEEL
ouva_rpc-1.23.3.dist-info/top_level.txt
ouva_rpc-1.23.3.dist-info/RECORD
