Metadata-Version: 2.1
Name: ouva-rpc
Version: 1.23.3
Summary: Ouva RPC package
Home-page: https://gitlab.com/ouvaco/ouva-protos
Author: Cagdas Bas
Author-email: cagdasbs@gmail.com
License: UNKNOWN
Platform: UNKNOWN
Requires-Python: >=3.6
Requires-Dist: protobuf
Provides-Extra: grpc
Requires-Dist: grpcio ; extra == 'grpc'
